exso/__init__.py
exso/__main__.py
exso/DataBase/DataBase.py
exso/DataBase/Status.py
exso/DataBase/Update.py
exso/DataBase/__init__.py
exso/DataLake/DataLake.py
exso/DataLake/Query.py
exso/DataLake/Status.py
exso/DataLake/Update.py
exso/DataLake/__init__.py
exso/DataLake/APIs/ADMIE.py
exso/DataLake/APIs/Assistant.py
exso/DataLake/APIs/HEnEx.py
exso/DataLake/APIs/HEnExArchives.py
exso/DataLake/APIs/StreamHandler.py
exso/DataLake/APIs/ZipHandler.py
exso/DataLake/APIs/__init__.py
exso/DataLake/ETL/ETL.py
exso/DataLake/ETL/FileReaders.py
exso/DataLake/ETL/__init__.py
exso/DataLake/Parsers/Operations.py
exso/DataLake/Parsers/PDFParsers.py
exso/DataLake/Parsers/ParsersArch.py
exso/DataLake/Parsers/ParsersHorizontal.py
exso/DataLake/Parsers/ParsersVerticalLong.py
exso/DataLake/Parsers/ParsersVerticalWide.py
exso/DataLake/Parsers/__init__.py
exso/Files/ReportsInfo.xlsx
exso/Files/__init__.py
exso/Files/refresh_requirements.txt
exso/Files/system_formats.txt
exso/Files/cuepoints/DAM_PreMarketSummary.txt
exso/Files/cuepoints/DAM_ResultsSummary.txt
exso/Files/cuepoints/DailyDispatchOfCreteElectricalSystem.txt
exso/Files/cuepoints/DayAheadRESForecast.txt
exso/Files/cuepoints/DayAheadScheduling.txt
exso/Files/cuepoints/ISPRequirements.txt
exso/Files/cuepoints/ISPResults.txt
exso/Files/cuepoints/LTPTRsNominationsSummary.txt
exso/Files/cuepoints/ReservoirFillingRate.txt
exso/Files/cuepoints/SystemRealizationSCADA.txt
exso/Files/cuepoints/UnitAvailabilities.txt
exso/Files/cuepoints/_info.txt
exso/Files/datalake_eligibility/DAM_HEnEx.txt
exso/Files/datalake_eligibility/HVCUSTCONS.txt
exso/Files/datalake_eligibility/IMBABE.txt
exso/Files/datalake_eligibility/LTPTRsNominationsSummary.txt
exso/Files/datalake_eligibility/MonthlyNTC.txt
exso/Files/datalake_eligibility/RESMV.txt
exso/Files/datalake_eligibility/RESMVLVPROD.txt
exso/Files/datalake_eligibility/generic.txt
exso/Files/renamers/Balancing.csv
exso/Files/renamers/DayAheadScheduling.csv
exso/Files/replacers/DayAheadLoadForecast.csv
exso-1.0.5.dist-info/METADATA
exso-1.0.5.dist-info/WHEEL
exso-1.0.5.dist-info/licenses/LICENSE.txt
exso-1.0.5.dist-info/RECORD
