Metadata-Version: 2.4
Name: exso
Version: 1.0.5
Summary: An analytical framework for the Greek Power&Gas System Operation ('SO') and Market Exchange ('Ex') Data.
Project-URL: Homepage, https://github.com/ThanosGkou/exso
Author-email: Thanos Natsikas <ath.natsikas@example.com>
Maintainer-email: Thanos Natsikas <ath.natsikas@example.com>
License: Attribution-NonCommercial-NoDerivatives 4.0 International
License-File: LICENSE.txt
Keywords: admie,energy-markets,greece,henex,ipto,power-exchange,system-operation
Classifier: Operating System :: Microsoft :: Windows :: Windows 10
Classifier: Programming Language :: Python :: 3
Requires-Python: >=3.10
Requires-Dist: beautifulsoup4>=4.11.2
Requires-Dist: colorama>=0.4.6
Requires-Dist: emoji>=2.5.0
Requires-Dist: fuzzywuzzy>=0.18.0
Requires-Dist: haggis>=0.8.0
Requires-Dist: matplotlib>=3.7.1
Requires-Dist: numpy>=1.24.2
Requires-Dist: openpyxl>=3.1.0
Requires-Dist: pandas>=1.5.3
Requires-Dist: plotly>=5.13.1
Requires-Dist: python-levenshtein>=0.21.0
Requires-Dist: requests>=2.28.2
Requires-Dist: rich>=13.3.2
Requires-Dist: seaborn>=0.12.2
Requires-Dist: seedir>=0.4.2
Requires-Dist: tqdm>=4.65.0
Requires-Dist: tzlocal>=4.3
Requires-Dist: unidecode>=1.3.6
Requires-Dist: xlrd>=1.0.0
